nomade/__init__.py
nomade/assets/pyproject.toml
nomade/assets/template.py.j2
nomade/constants/level.py
nomade/database.py
nomade/main.py
nomade/migration.py
nomade/migrations.py
nomade/nomad.py
nomade/settings.py
nomade/utils.py
nomade-1.0.0.dist-info/entry_points.txt
nomade-1.0.0.dist-info/LICENSE
nomade-1.0.0.dist-info/WHEEL
nomade-1.0.0.dist-info/METADATA
nomade-1.0.0.dist-info/RECORD
