Metadata-Version: 2.1
Name: nomade
Version: 1.0.0
Summary: Migration Manager for Humans
Home-page: https://github.com/kelvins/nomade
License: Apache-2.0
Author: Kelvin S. do Prado
Author-email: kelvinpfw@gmail.com
Requires-Python: >=3.7,<4.0
Classifier: License :: OSI Approved :: Apache Software License
Classifier: Programming Language :: Python :: 3
Classifier: Programming Language :: Python :: 3.7
Requires-Dist: Jinja2 (==2.10.1)
Requires-Dist: click (>=7.0,<8.0)
Requires-Dist: sqlalchemy (>=1.3,<2.0)
Requires-Dist: toml (>=0.10.0,<0.11.0)
Project-URL: Repository, https://github.com/kelvins/nomade
